{
	"activeTaskName": "excel",
	"tasks": [
		{
			"name": "default",
			"files": [
				{
					"filepath": "\\vue.html",
					"marks": [
						12,
						325
					]
				}
			]
		},
		{
			"name": "vue",
			"files": [
				{
					"filepath": "\\vue\\vuetifi.html",
					"marks": [
						547
					]
				},
				{
					"filepath": "\\vuetifi.html",
					"marks": [
						717
					]
				}
			]
		},
		{
			"name": "vue hechizo",
			"files": [
				{
					"filepath": "\\vue.html",
					"marks": [
						596,
						767,
						859
					]
				},
				{
					"filepath": "\\js\\habilidades.js",
					"marks": [
						1483
					]
				}
			]
		},
		{
			"name": "monedas y objetos",
			"files": [
				{
					"filepath": "\\vue.html",
					"marks": [
						12,
						318,
						407,
						469,
						64,
						932,
						997
					]
				}
			]
		},
		{
			"name": "excel",
			"files": [
				{
					"filepath": "\\ex.js",
					"marks": [
						290
					]
				}
			]
		}
	]
}